stockPricePredictor/__init__.py
stockPricePredictor/stockpricepredictor.py
stockPricePredictor-1.0.3.dist-info/METADATA
stockPricePredictor-1.0.3.dist-info/WHEEL
stockPricePredictor-1.0.3.dist-info/top_level.txt
stockPricePredictor-1.0.3.dist-info/RECORD
